serpen-0.4.7.dist-info/METADATA
serpen-0.4.7.dist-info/WHEEL
serpen-0.4.7.dist-info/licenses/LICENSE
serpen/__main__.py
serpen/__init__.py
serpen/py.typed
serpen-0.4.7.data/scripts/debug_analyzer
serpen-0.4.7.data/scripts/serpen
serpen-0.4.7.dist-info/RECORD
