Metadata-Version: 2.3
Name: serpen
Version: 0.4.7
Classifier: Development Status :: 3 - Alpha
Classifier: Intended Audience :: Developers
Classifier: License :: OSI Approved :: MIT License
Classifier: Programming Language :: Python :: 3
Classifier: Programming Language :: Python :: 3.10
Classifier: Programming Language :: Python :: 3.11
Classifier: Programming Language :: Python :: 3.12
Classifier: Programming Language :: Rust
Classifier: Topic :: Software Development :: Build Tools
Classifier: Topic :: Software Development :: Libraries :: Python Modules
License-File: LICENSE
Summary: Python source bundler that produces a single .py file from multi-module projects
Keywords: bundler,python,deployment,pyspark,lambda
Author: Konstantin Vyatkin <tino@vtkn.io>
Author-email: Konstantin Vyatkin <tino@vtkn.io>
License: MIT
Requires-Python: >=3.7
Project-URL: Homepage, https://github.com/tinovyatkin/serpen
Project-URL: Repository, https://github.com/tinovyatkin/serpen
Project-URL: Documentation, https://github.com/tinovyatkin/serpen#readme
Project-URL: Issues, https://github.com/tinovyatkin/serpen/issues
